slackmq.py
slackmq-0.1.2.dist-info/LICENSE
slackmq-0.1.2.dist-info/METADATA
slackmq-0.1.2.dist-info/WHEEL
slackmq-0.1.2.dist-info/top_level.txt
slackmq-0.1.2.dist-info/RECORD
