Metadata-Version: 2.1
Name: slackmq
Version: 0.1.2
Summary: A Slack Message Queue system
Home-page: https://github.com/meltaxa/slackmq
Author: Dennis Mellican
Author-email: dennis@mellican.com
License: MIT
Platform: UNKNOWN
Classifier: Development Status :: 4 - Beta
Classifier: License :: OSI Approved :: MIT License
Classifier: Operating System :: OS Independent
Classifier: Programming Language :: Python
Classifier: Programming Language :: Python :: 2
Classifier: Programming Language :: Python :: 2.7
Classifier: Programming Language :: Python :: 3
Classifier: Programming Language :: Python :: 3.4
Classifier: Programming Language :: Python :: 3.5
Classifier: Programming Language :: Python :: 3.6
Requires-Dist: slacker (>=0.9.50)
